algorin/__init__.py
algorin/chatbot.py
algorin/file_extractor.py
algorin/main.py
algorin-cli/__init__.py
algorin-cli/chatbot.py
algorin-cli/file_extractor.py
algorin-cli/main.py
tests/__init__.py
tests/test_chatbot.py
tests/test_file_extractor.py
tests/test_main.py
algorin_cli-0.21.dist-info/METADATA
algorin_cli-0.21.dist-info/WHEEL
algorin_cli-0.21.dist-info/entry_points.txt
algorin_cli-0.21.dist-info/top_level.txt
algorin_cli-0.21.dist-info/RECORD
