Metadata-Version: 2.1
Name: algorin-cli
Version: 0.21
Summary: Acceso a GPT-3 y procesamiento de documentos desde la línea de comandos.
Home-page: https://github.com/Jorge-Polanco-Roque/bot_cli
Author: JP
Author-email: jorge.polanco@itesm.mx
License: MIT
Classifier: Programming Language :: Python :: 3
Classifier: License :: OSI Approved :: MIT License
Classifier: Operating System :: OS Independent
Requires-Dist: aiohttp ==3.9.3
Requires-Dist: aiosignal ==1.3.1
Requires-Dist: annotated-types ==0.6.0
Requires-Dist: anyio ==4.2.0
Requires-Dist: appdirs ==1.4.4
Requires-Dist: appnope ==0.1.4
Requires-Dist: asttokens ==2.4.1
Requires-Dist: attrs ==23.2.0
Requires-Dist: backoff ==2.2.1
Requires-Dist: backports.tarfile ==1.1.0
Requires-Dist: beautifulsoup4 ==4.12.3
Requires-Dist: bitarray ==2.9.2
Requires-Dist: blinker ==1.7.0
Requires-Dist: cachetools ==5.3.3
Requires-Dist: certifi ==2024.2.2
Requires-Dist: chardet ==5.2.0
Requires-Dist: charset-normalizer ==3.3.2
Requires-Dist: chroma-hnswlib ==0.7.2
Requires-Dist: chromadb ==0.4.6
Requires-Dist: click ==8.1.7
Requires-Dist: coloredlogs ==15.0.1
Requires-Dist: comm ==0.2.2
Requires-Dist: dataclasses-json ==0.6.4
Requires-Dist: dataclasses-json-speakeasy ==0.5.11
Requires-Dist: datasets ==2.18.0
Requires-Dist: debugpy ==1.8.1
Requires-Dist: decorator ==4.4.2
Requires-Dist: decouple ==0.0.7
Requires-Dist: dill ==0.3.8
Requires-Dist: diskcache ==5.6.3
Requires-Dist: distro ==1.9.0
Requires-Dist: docker ==7.0.0
Requires-Dist: docstring-parser ==0.16
Requires-Dist: docutils ==0.21.1
Requires-Dist: emoji ==2.10.1
Requires-Dist: exceptiongroup ==1.2.0
Requires-Dist: executing ==2.0.1
Requires-Dist: faiss-cpu ==1.8.0
Requires-Dist: fastapi ==0.99.1
Requires-Dist: filelock ==3.13.1
Requires-Dist: filetype ==1.2.0
Requires-Dist: FLAML ==2.1.1
Requires-Dist: Flask ==2.3.3
Requires-Dist: flatbuffers ==23.5.26
Requires-Dist: frozenlist ==1.4.1
Requires-Dist: fsspec ==2024.2.0
Requires-Dist: google-api-core ==2.18.0
Requires-Dist: google-auth ==2.29.0
Requires-Dist: google-cloud-aiplatform ==1.48.0
Requires-Dist: google-cloud-bigquery ==3.20.1
Requires-Dist: google-cloud-core ==2.4.1
Requires-Dist: google-cloud-resource-manager ==1.12.3
Requires-Dist: google-cloud-storage ==2.16.0
Requires-Dist: google-crc32c ==1.5.0
Requires-Dist: google-resumable-media ==2.7.0
Requires-Dist: googleapis-common-protos ==1.63.0
Requires-Dist: grpc-google-iam-v1 ==0.13.0
Requires-Dist: grpcio ==1.62.1
Requires-Dist: grpcio-status ==1.62.1
Requires-Dist: gTTS ==2.5.1
Requires-Dist: h11 ==0.14.0
Requires-Dist: httpcore ==1.0.3
Requires-Dist: httptools ==0.6.1
Requires-Dist: httpx ==0.26.0
Requires-Dist: huggingface-hub ==0.21.3
Requires-Dist: humanfriendly ==10.0
Requires-Dist: idna ==3.6
Requires-Dist: imageio ==2.34.0
Requires-Dist: imageio-ffmpeg ==0.4.9
Requires-Dist: importlib-metadata ==7.1.0
Requires-Dist: importlib-resources ==6.1.2
Requires-Dist: iniconfig ==2.0.0
Requires-Dist: ipykernel ==6.29.4
Requires-Dist: ipython ==8.23.0
Requires-Dist: itsdangerous ==2.1.2
Requires-Dist: jaraco.classes ==3.4.0
Requires-Dist: jaraco.context ==5.3.0
Requires-Dist: jaraco.functools ==4.0.0
Requires-Dist: jedi ==0.19.1
Requires-Dist: Jinja2 ==3.1.3
Requires-Dist: joblib ==1.3.2
Requires-Dist: jsonpatch ==1.33
Requires-Dist: jsonpath-python ==1.0.6
Requires-Dist: jsonpointer ==2.4
Requires-Dist: jupyter-client ==8.6.1
Requires-Dist: jupyter-core ==5.7.2
Requires-Dist: keyring ==25.1.0
Requires-Dist: langchain ==0.1.9
Requires-Dist: langchain-community ==0.0.27
Requires-Dist: langchain-core ==0.1.30
Requires-Dist: langchain-openai ==0.0.8
Requires-Dist: langdetect ==1.0.9
Requires-Dist: langgraph ==0.0.29
Requires-Dist: langsmith ==0.1.10
Requires-Dist: llvmlite ==0.42.0
Requires-Dist: lxml ==5.1.0
Requires-Dist: markdown-it-py ==3.0.0
Requires-Dist: MarkupSafe ==2.1.5
Requires-Dist: marshmallow ==3.20.2
Requires-Dist: matplotlib-inline ==0.1.7
Requires-Dist: mdurl ==0.1.2
Requires-Dist: monotonic ==1.6
Requires-Dist: more-itertools ==10.2.0
Requires-Dist: moviepy ==1.0.3
Requires-Dist: mpmath ==1.3.0
Requires-Dist: multidict ==6.0.5
Requires-Dist: multiprocess ==0.70.16
Requires-Dist: mypy-extensions ==1.0.0
Requires-Dist: nest-asyncio ==1.6.0
Requires-Dist: networkx ==3.2.1
Requires-Dist: nh3 ==0.2.17
Requires-Dist: nltk ==3.8.1
Requires-Dist: numba ==0.59.0
Requires-Dist: numpy ==1.26.4
Requires-Dist: onnxruntime ==1.17.1
Requires-Dist: openai ==1.21.2
Requires-Dist: openai-whisper ==20231117
Requires-Dist: opencv-python-headless ==4.9.0.80
Requires-Dist: orjson ==3.9.15
Requires-Dist: overrides ==7.7.0
Requires-Dist: packaging ==23.2
Requires-Dist: pandas ==2.2.1
Requires-Dist: parso ==0.8.4
Requires-Dist: pdfreader ==0.1.12
Requires-Dist: pexpect ==4.9.0
Requires-Dist: pickleshare ==0.7.5
Requires-Dist: pillow ==10.2.0
Requires-Dist: pkginfo ==1.10.0
Requires-Dist: platformdirs ==4.2.0
Requires-Dist: pluggy ==1.4.0
Requires-Dist: posthog ==3.4.2
Requires-Dist: proglog ==0.1.10
Requires-Dist: prompt-toolkit ==3.0.43
Requires-Dist: proto-plus ==1.23.0
Requires-Dist: protobuf ==4.25.3
Requires-Dist: psutil ==5.9.8
Requires-Dist: ptyprocess ==0.7.0
Requires-Dist: pulsar-client ==3.4.0
Requires-Dist: pure-eval ==0.2.2
Requires-Dist: pyarrow ==15.0.2
Requires-Dist: pyarrow-hotfix ==0.6
Requires-Dist: pyasn1 ==0.6.0
Requires-Dist: pyasn1-modules ==0.4.0
Requires-Dist: pyautogen ==0.2.13
Requires-Dist: pycryptodome ==3.20.0
Requires-Dist: pydantic ==1.10.0
Requires-Dist: pydantic-core ==2.16.2
Requires-Dist: pyee ==11.1.0
Requires-Dist: Pygments ==2.17.2
Requires-Dist: PyMuPDF ==1.23.26
Requires-Dist: PyMuPDFb ==1.23.22
Requires-Dist: PyPDF2 ==3.0.1
Requires-Dist: PyPika ==0.48.9
Requires-Dist: pysbd ==0.3.4
Requires-Dist: pytesseract ==0.3.10
Requires-Dist: pytest ==8.1.1
Requires-Dist: pytest-mock ==3.14.0
Requires-Dist: python-dateutil ==2.8.2
Requires-Dist: python-decouple ==3.8
Requires-Dist: python-docx ==1.1.0
Requires-Dist: python-dotenv ==1.0.1
Requires-Dist: python-iso639 ==2024.2.7
Requires-Dist: python-magic ==0.4.27
Requires-Dist: python-pptx ==0.6.23
Requires-Dist: pytube ==15.0.0
Requires-Dist: pytz ==2024.1
Requires-Dist: PyYAML ==6.0.1
Requires-Dist: pyzmq ==26.0.0
Requires-Dist: ragas ==0.1.6
Requires-Dist: rapidfuzz ==3.6.1
Requires-Dist: readme-renderer ==43.0
Requires-Dist: regex ==2023.12.25
Requires-Dist: requests ==2.31.0
Requires-Dist: requests-toolbelt ==1.0.0
Requires-Dist: rfc3986 ==2.0.0
Requires-Dist: rich ==13.7.1
Requires-Dist: rsa ==4.9
Requires-Dist: safetensors ==0.4.2
Requires-Dist: scikit-learn ==1.4.1.post1
Requires-Dist: scipy ==1.12.0
Requires-Dist: sentence-transformers ==2.5.0
Requires-Dist: shapely ==2.0.4
Requires-Dist: six ==1.16.0
Requires-Dist: slack-sdk ==3.27.1
Requires-Dist: slackclient ==2.9.4
Requires-Dist: slackeventsapi ==3.0.1
Requires-Dist: sniffio ==1.3.0
Requires-Dist: soupsieve ==2.5
Requires-Dist: SQLAlchemy ==2.0.27
Requires-Dist: stack-data ==0.6.3
Requires-Dist: starlette ==0.27.0
Requires-Dist: sympy ==1.12
Requires-Dist: tabulate ==0.9.0
Requires-Dist: tenacity ==8.2.3
Requires-Dist: termcolor ==2.4.0
Requires-Dist: threadpoolctl ==3.3.0
Requires-Dist: tiktoken ==0.6.0
Requires-Dist: tokenizers ==0.15.2
Requires-Dist: torch ==2.1.2
Requires-Dist: tornado ==6.4
Requires-Dist: tqdm ==4.66.2
Requires-Dist: traitlets ==5.14.2
Requires-Dist: transformers ==4.38.1
Requires-Dist: twine ==5.0.0
Requires-Dist: typing-inspect ==0.9.0
Requires-Dist: typing-extensions ==4.9.0
Requires-Dist: tzdata ==2024.1
Requires-Dist: unstructured ==0.13.0
Requires-Dist: unstructured-client ==0.18.0
Requires-Dist: urllib3 ==1.26.18
Requires-Dist: uvicorn ==0.27.1
Requires-Dist: uvloop ==0.19.0
Requires-Dist: vision-agent ==0.0.46
Requires-Dist: watchfiles ==0.21.0
Requires-Dist: wcwidth ==0.2.13
Requires-Dist: websockets ==12.0
Requires-Dist: Werkzeug ==3.0.1
Requires-Dist: wrapt ==1.16.0
Requires-Dist: XlsxWriter ==3.2.0
Requires-Dist: xxhash ==3.4.1
Requires-Dist: yarl ==1.9.4
Requires-Dist: yolk3k ==0.9
Requires-Dist: youtube-dl ==2021.12.17
Requires-Dist: zipp ==3.18.1
